pca9632/__init__.py
pca9632/controller.py
pca9632-0.1.0.dist-info/WHEEL
pca9632-0.1.0.dist-info/METADATA
pca9632-0.1.0.dist-info/RECORD
