Metadata-Version: 2.1
Name: pca9632
Version: 0.1.0
Summary: PCA9632 driver
Home-page: https://github.com/jveitchmichaelis/pca9632
Author: Josh Veitch-Michaelis
Author-email: j.veitchmichaelis@gmail.com
Requires-Python: >=2.7, !=3.0.*, !=3.1.*, !=3.2.*, !=3.3.*, !=3.4.*
Classifier: Programming Language :: Python :: 2
Classifier: Programming Language :: Python :: 2.7
Classifier: Programming Language :: Python :: 3
Classifier: Programming Language :: Python :: 3.5
Classifier: Programming Language :: Python :: 3.6
Classifier: Programming Language :: Python :: 3.7
Classifier: Programming Language :: Python :: 3.8
Requires-Dist: smbus2 (>=0.3.0,<0.4.0)
Project-URL: Repository, https://github.com/jveitchmichaelis/pca9632
